agrothon_client/__init__.py
agrothon_client/__main__.py
agrothon_client/request_helper.py
agrothon_client/utils.py
AgroClient-1.1.3.dist-info/LICENSE
AgroClient-1.1.3.dist-info/METADATA
AgroClient-1.1.3.dist-info/WHEEL
AgroClient-1.1.3.dist-info/entry_points.txt
AgroClient-1.1.3.dist-info/top_level.txt
AgroClient-1.1.3.dist-info/RECORD
