Metadata-Version: 2.1
Name: AgroClient
Version: 1.1.3
Summary: A Client module for Agrothon
Home-page: https://github.com/viswanathbalusu/Agrothon-Client
Author: viswanathbalusu
Author-email: ckvbalusu@gmail.com
License: AGPL3.0
Platform: any
Classifier: Programming Language :: Python :: 3
Classifier: Programming Language :: Python :: 3.7
Classifier: Programming Language :: Python :: 3.8
Classifier: Programming Language :: Python :: 3.9
Classifier: License :: OSI Approved :: GNU Affero General Public License v3 or later (AGPLv3+)
Classifier: Operating System :: POSIX :: Linux
Classifier: Development Status :: 5 - Production/Stable
Requires-Python: >=3.7
Requires-Dist: requests (==2.25.1)
Requires-Dist: gpiozero (==1.5.1)
Requires-Dist: pyserial (==3.5)
Requires-Dist: opencv-python (==4.5.1.48)
Requires-Dist: RPi.GPIO (==0.7.0)
